{
  "per_series": {
    "24C": {
      "color_hex": "#0000FF",
      "source_px": 1866,
      "replot_px": 2628,
      "intersection_px": 912,
      "union_px": 3582,
      "iou": 0.2546
    },
    "27C": {
      "color_hex": "#00FF00",
      "source_px": 0,
      "replot_px": 3621,
      "intersection_px": 0,
      "union_px": 3621,
      "iou": 0.0
    },
    "30C": {
      "color_hex": "#FF0000",
      "source_px": 1413,
      "replot_px": 3231,
      "intersection_px": 1349,
      "union_px": 3295,
      "iou": 0.4094
    },
    "IF_24C": {
      "color_hex": "#0000FF",
      "source_px": 1866,
      "replot_px": 2628,
      "intersection_px": 912,
      "union_px": 3582,
      "iou": 0.2546
    },
    "IF_27C": {
      "color_hex": "#00FF00",
      "source_px": 0,
      "replot_px": 3621,
      "intersection_px": 0,
      "union_px": 3621,
      "iou": 0.0
    },
    "IF_30C": {
      "color_hex": "#FF0000",
      "source_px": 1413,
      "replot_px": 3231,
      "intersection_px": 1349,
      "union_px": 3295,
      "iou": 0.4094
    }
  },
  "mean_iou": 0.2213,
  "weighted_iou": 0.2101
}