{
  "per_series": {
    "24C": {
      "claims": 18,
      "source_components": 48,
      "unclaimed": [
        {
          "col": 502,
          "row": 154,
          "area": 9,
          "aspect": 1.0,
          "triage": "likely-marker"
        },
        {
          "col": 491,
          "row": 166,
          "area": 10,
          "aspect": 1.2,
          "triage": "likely-marker"
        },
        {
          "col": 480,
          "row": 177,
          "area": 7,
          "aspect": 1.0,
          "triage": "likely-noise"
        },
        {
          "col": 470,
          "row": 189,
          "area": 6,
          "aspect": 1.0,
          "triage": "likely-noise"
        },
        {
          "col": 459,
          "row": 200,
          "area": 6,
          "aspect": 1.0,
          "triage": "likely-noise"
        },
        {
          "col": 448,
          "row": 212,
          "area": 9,
          "aspect": 1.2,
          "triage": "likely-marker"
        },
        {
          "col": 438,
          "row": 223,
          "area": 7,
          "aspect": 1.0,
          "triage": "likely-noise"
        },
        {
          "col": 433,
          "row": 228,
          "area": 6,
          "aspect": 1.0,
          "triage": "likely-noise"
        },
        {
          "col": 421,
          "row": 238,
          "area": 7,
          "aspect": 1.0,
          "triage": "likely-noise"
        },
        {
          "col": 410,
          "row": 248,
          "area": 8,
          "aspect": 1.2,
          "triage": "likely-marker"
        },
        {
          "col": 398,
          "row": 258,
          "area": 8,
          "aspect": 1.2,
          "triage": "likely-marker"
        },
        {
          "col": 319,
          "row": 298,
          "area": 669,
          "aspect": 4.33,
          "triage": "likely-other"
        },
        {
          "col": 386,
          "row": 269,
          "area": 7,
          "aspect": 1.0,
          "triage": "likely-noise"
        },
        {
          "col": 374,
          "row": 279,
          "area": 8,
          "aspect": 1.2,
          "triage": "likely-marker"
        },
        {
          "col": 363,
          "row": 289,
          "area": 4,
          "aspect": 1.0,
          "triage": "likely-noise"
        },
        {
          "col": 351,
          "row": 297,
          "area": 5,
          "aspect": 1.67,
          "triage": "likely-noise"
        },
        {
          "col": 318,
          "row": 344,
          "area": 92,
          "aspect": 1.1,
          "triage": "likely-marker"
        },
        {
          "col": 287,
          "row": 342,
          "area": 6,
          "aspect": 1.67,
          "triage": "likely-noise"
        },
        {
          "col": 279,
          "row": 348,
          "area": 7,
          "aspect": 1.75,
          "triage": "likely-noise"
        },
        {
          "col": 318,
          "row": 356,
          "area": 94,
          "aspect": 1.0,
          "triage": "likely-marker"
        },
        {
          "col": 266,
          "row": 355,
          "area": 7,
          "aspect": 1.5,
          "triage": "likely-noise"
        },
        {
          "col": 848,
          "row": 369,
          "area": 7,
          "aspect": 7.0,
          "triage": "likely-noise"
        },
        {
          "col": 192,
          "row": 395,
          "area": 8,
          "aspect": 2.33,
          "triage": "likely-line-fragment"
        },
        {
          "col": 178,
          "row": 402,
          "area": 8,
          "aspect": 1.5,
          "triage": "likely-marker"
        },
        {
          "col": 164,
          "row": 408,
          "area": 6,
          "aspect": 2.0,
          "triage": "likely-noise"
        },
        {
          "col": 149,
          "row": 415,
          "area": 7,
          "aspect": 1.75,
          "triage": "likely-noise"
        },
        {
          "col": 137,
          "row": 421,
          "area": 4,
          "aspect": 2.0,
          "triage": "likely-noise"
        },
        {
          "col": 104,
          "row": 433,
          "area": 6,
          "aspect": 2.0,
          "triage": "likely-noise"
        },
        {
          "col": 88,
          "row": 439,
          "area": 7,
          "aspect": 2.33,
          "triage": "likely-noise"
        },
        {
          "col": 74,
          "row": 444,
          "area": 8,
          "aspect": 2.33,
          "triage": "likely-line-fragment"
        }
      ]
    },
    "27C": {
      "claims": 19,
      "source_components": 0,
      "unclaimed": []
    },
    "30C": {
      "claims": 20,
      "source_components": 95,
      "unclaimed": []
    },
    "IF_24C": {
      "claims": 0,
      "source_components": 48,
      "unclaimed": [
        {
          "col": 502,
          "row": 154,
          "area": 9,
          "aspect": 1.0,
          "triage": "likely-marker"
        },
        {
          "col": 491,
          "row": 166,
          "area": 10,
          "aspect": 1.2,
          "triage": "likely-marker"
        },
        {
          "col": 480,
          "row": 177,
          "area": 7,
          "aspect": 1.0,
          "triage": "likely-noise"
        },
        {
          "col": 470,
          "row": 189,
          "area": 6,
          "aspect": 1.0,
          "triage": "likely-noise"
        },
        {
          "col": 459,
          "row": 200,
          "area": 6,
          "aspect": 1.0,
          "triage": "likely-noise"
        },
        {
          "col": 448,
          "row": 212,
          "area": 9,
          "aspect": 1.2,
          "triage": "likely-marker"
        },
        {
          "col": 438,
          "row": 223,
          "area": 7,
          "aspect": 1.0,
          "triage": "likely-noise"
        },
        {
          "col": 433,
          "row": 228,
          "area": 6,
          "aspect": 1.0,
          "triage": "likely-noise"
        },
        {
          "col": 421,
          "row": 238,
          "area": 7,
          "aspect": 1.0,
          "triage": "likely-noise"
        },
        {
          "col": 410,
          "row": 248,
          "area": 8,
          "aspect": 1.2,
          "triage": "likely-marker"
        },
        {
          "col": 327,
          "row": 254,
          "area": 90,
          "aspect": 1.1,
          "triage": "likely-marker"
        },
        {
          "col": 398,
          "row": 258,
          "area": 8,
          "aspect": 1.2,
          "triage": "likely-marker"
        },
        {
          "col": 319,
          "row": 298,
          "area": 669,
          "aspect": 4.33,
          "triage": "likely-other"
        },
        {
          "col": 386,
          "row": 269,
          "area": 7,
          "aspect": 1.0,
          "triage": "likely-noise"
        },
        {
          "col": 374,
          "row": 279,
          "area": 8,
          "aspect": 1.2,
          "triage": "likely-marker"
        },
        {
          "col": 363,
          "row": 289,
          "area": 4,
          "aspect": 1.0,
          "triage": "likely-noise"
        },
        {
          "col": 351,
          "row": 297,
          "area": 5,
          "aspect": 1.67,
          "triage": "likely-noise"
        },
        {
          "col": 300,
          "row": 334,
          "area": 7,
          "aspect": 1.5,
          "triage": "likely-noise"
        },
        {
          "col": 318,
          "row": 344,
          "area": 92,
          "aspect": 1.1,
          "triage": "likely-marker"
        },
        {
          "col": 287,
          "row": 342,
          "area": 6,
          "aspect": 1.67,
          "triage": "likely-noise"
        },
        {
          "col": 279,
          "row": 348,
          "area": 7,
          "aspect": 1.75,
          "triage": "likely-noise"
        },
        {
          "col": 318,
          "row": 356,
          "area": 94,
          "aspect": 1.0,
          "triage": "likely-marker"
        },
        {
          "col": 266,
          "row": 355,
          "area": 7,
          "aspect": 1.5,
          "triage": "likely-noise"
        },
        {
          "col": 252,
          "row": 363,
          "area": 8,
          "aspect": 1.5,
          "triage": "likely-marker"
        },
        {
          "col": 309,
          "row": 369,
          "area": 88,
          "aspect": 1.0,
          "triage": "likely-marker"
        },
        {
          "col": 238,
          "row": 371,
          "area": 9,
          "aspect": 1.75,
          "triage": "likely-marker"
        },
        {
          "col": 848,
          "row": 369,
          "area": 7,
          "aspect": 7.0,
          "triage": "likely-noise"
        },
        {
          "col": 224,
          "row": 379,
          "area": 9,
          "aspect": 1.75,
          "triage": "likely-marker"
        },
        {
          "col": 290,
          "row": 382,
          "area": 93,
          "aspect": 1.0,
          "triage": "likely-marker"
        },
        {
          "col": 212,
          "row": 386,
          "area": 4,
          "aspect": 2.0,
          "triage": "likely-noise"
        },
        {
          "col": 205,
          "row": 390,
          "area": 5,
          "aspect": 2.0,
          "triage": "likely-noise"
        },
        {
          "col": 290,
          "row": 396,
          "area": 91,
          "aspect": 1.0,
          "triage": "likely-marker"
        },
        {
          "col": 192,
          "row": 395,
          "area": 8,
          "aspect": 2.33,
          "triage": "likely-line-fragment"
        },
        {
          "col": 178,
          "row": 402,
          "area": 8,
          "aspect": 1.5,
          "triage": "likely-marker"
        },
        {
          "col": 196,
          "row": 410,
          "area": 96,
          "aspect": 1.0,
          "triage": "likely-marker"
        },
        {
          "col": 164,
          "row": 408,
          "area": 6,
          "aspect": 2.0,
          "triage": "likely-noise"
        },
        {
          "col": 149,
          "row": 415,
          "area": 7,
          "aspect": 1.75,
          "triage": "likely-noise"
        },
        {
          "col": 114,
          "row": 425,
          "area": 100,
          "aspect": 1.36,
          "triage": "likely-marker"
        },
        {
          "col": 137,
          "row": 421,
          "area": 4,
          "aspect": 2.0,
          "triage": "likely-noise"
        },
        {
          "col": 104,
          "row": 433,
          "area": 6,
          "aspect": 2.0,
          "triage": "likely-noise"
        },
        {
          "col": 59,
          "row": 441,
          "area": 49,
          "aspect": 1.83,
          "triage": "likely-marker"
        },
        {
          "col": 88,
          "row": 439,
          "area": 7,
          "aspect": 2.33,
          "triage": "likely-noise"
        },
        {
          "col": 74,
          "row": 444,
          "area": 8,
          "aspect": 2.33,
          "triage": "likely-line-fragment"
        },
        {
          "col": 60,
          "row": 450,
          "area": 5,
          "aspect": 2.5,
          "triage": "likely-noise"
        }
      ]
    },
    "IF_27C": {
      "claims": 0,
      "source_components": 0,
      "unclaimed": []
    },
    "IF_30C": {
      "claims": 0,
      "source_components": 95,
      "unclaimed": [
        {
          "col": 527,
          "row": 118,
          "area": 57,
          "aspect": 1.0,
          "triage": "likely-marker"
        },
        {
          "col": 527,
          "row": 132,
          "area": 55,
          "aspect": 1.0,
          "triage": "likely-marker"
        },
        {
          "col": 519,
          "row": 146,
          "area": 50,
          "aspect": 1.11,
          "triage": "likely-marker"
        },
        {
          "col": 519,
          "row": 160,
          "area": 52,
          "aspect": 1.11,
          "triage": "likely-marker"
        },
        {
          "col": 519,
          "row": 174,
          "area": 56,
          "aspect": 1.11,
          "triage": "likely-marker"
        },
        {
          "col": 519,
          "row": 188,
          "area": 50,
          "aspect": 1.11,
          "triage": "likely-marker"
        },
        {
          "col": 503,
          "row": 202,
          "area": 60,
          "aspect": 1.0,
          "triage": "likely-marker"
        },
        {
          "col": 503,
          "row": 216,
          "area": 60,
          "aspect": 1.1,
          "triage": "likely-marker"
        },
        {
          "col": 487,
          "row": 230,
          "area": 61,
          "aspect": 1.0,
          "triage": "likely-marker"
        },
        {
          "col": 471,
          "row": 245,
          "area": 56,
          "aspect": 1.0,
          "triage": "likely-marker"
        },
        {
          "col": 463,
          "row": 260,
          "area": 54,
          "aspect": 1.11,
          "triage": "likely-marker"
        },
        {
          "col": 463,
          "row": 275,
          "area": 54,
          "aspect": 1.11,
          "triage": "likely-marker"
        },
        {
          "col": 456,
          "row": 290,
          "area": 58,
          "aspect": 1.0,
          "triage": "likely-marker"
        },
        {
          "col": 447,
          "row": 306,
          "area": 60,
          "aspect": 1.1,
          "triage": "likely-marker"
        },
        {
          "col": 376,
          "row": 322,
          "area": 58,
          "aspect": 1.0,
          "triage": "likely-marker"
        },
        {
          "col": 304,
          "row": 339,
          "area": 57,
          "aspect": 1.0,
          "triage": "likely-marker"
        },
        {
          "col": 231,
          "row": 357,
          "area": 63,
          "aspect": 1.1,
          "triage": "likely-marker"
        },
        {
          "col": 112,
          "row": 376,
          "area": 59,
          "aspect": 1.1,
          "triage": "likely-marker"
        },
        {
          "col": 64,
          "row": 397,
          "area": 60,
          "aspect": 1.1,
          "triage": "likely-marker"
        },
        {
          "col": 58,
          "row": 420,
          "area": 34,
          "aspect": 2.2,
          "triage": "likely-line-fragment"
        }
      ]
    }
  },
  "summary": {
    "total_unclaimed_likely_marker": 47,
    "total_unclaimed_likely_other": 47
  }
}