{
  "corpus": "synthetic-r4-1",
  "extractor": "graph-data-extraction",
  "results_dir": "results-v3",
  "n_charts": 10,
  "charts": {
    "01-linear-scatter": {
      "error": "missing extractor dir: /Users/csweet1/Documents/projects/CRS_research/figure-recovery-suite/extractors/graph-data-extraction/results-v3/synthetic-r4-1/01-linear-scatter"
    },
    "02-simple-bar": {
      "x_tol": 0.5,
      "y_tol": 0.5,
      "scatter": {
        "summary": {
          "tp": 6,
          "fn": 0,
          "fp": 0,
          "precision": 1.0,
          "recall": 1.0,
          "f1": 1.0,
          "jaccard": 1.0
        },
        "gt_n": 6,
        "mine_n": 6,
        "by_series": {
          "throughput": {
            "gt_label": "throughput",
            "tp": 6,
            "fn": 0,
            "fp": 0,
            "gt_n": 6,
            "mine_n": 6
          }
        }
      },
      "curves": {
        "summary": {
          "tp": 0,
          "fn": 0,
          "fp": 0,
          "precision": 0.0,
          "recall": 0.0,
          "f1": 0.0,
          "jaccard": 0.0
        },
        "gt_n": 0,
        "mine_n": 0,
        "by_series": {}
      },
      "errbars": {
        "summary": {
          "tp": 0,
          "fn": 0,
          "fp": 0,
          "precision": 0.0,
          "recall": 0.0,
          "f1": 0.0,
          "jaccard": 0.0
        },
        "gt_n": 0,
        "mine_n": 0,
        "by_series": {}
      },
      "combined": {
        "tp": 6,
        "fn": 0,
        "fp": 0,
        "precision": 1.0,
        "recall": 1.0,
        "f1": 1.0,
        "jaccard": 1.0
      }
    },
    "03-grouped-bar-errbars": {
      "x_tol": 1.5,
      "y_tol": 2.0,
      "scatter": {
        "summary": {
          "tp": 15,
          "fn": 0,
          "fp": 0,
          "precision": 1.0,
          "recall": 1.0,
          "f1": 1.0,
          "jaccard": 1.0
        },
        "gt_n": 15,
        "mine_n": 15,
        "by_series": {
          "baseline": {
            "gt_label": "baseline",
            "tp": 5,
            "fn": 0,
            "fp": 0,
            "gt_n": 5,
            "mine_n": 5
          },
          "tuned": {
            "gt_label": "tuned",
            "tp": 5,
            "fn": 0,
            "fp": 0,
            "gt_n": 5,
            "mine_n": 5
          },
          "tunedjit": {
            "gt_label": "tunedjit",
            "tp": 5,
            "fn": 0,
            "fp": 0,
            "gt_n": 5,
            "mine_n": 5
          }
        }
      },
      "curves": {
        "summary": {
          "tp": 0,
          "fn": 0,
          "fp": 0,
          "precision": 0.0,
          "recall": 0.0,
          "f1": 0.0,
          "jaccard": 0.0
        },
        "gt_n": 0,
        "mine_n": 0,
        "by_series": {}
      },
      "errbars": {
        "summary": {
          "tp": 30,
          "fn": 0,
          "fp": 0,
          "precision": 1.0,
          "recall": 1.0,
          "f1": 1.0,
          "jaccard": 1.0
        },
        "gt_n": 30,
        "mine_n": 30,
        "by_series": {
          "errbar_caps_pooled": {
            "schema": "ErrorBarLayer",
            "tp": 30,
            "fn": 0,
            "fp": 0,
            "gt_n": 30,
            "mine_n": 30
          }
        }
      },
      "combined": {
        "tp": 45,
        "fn": 0,
        "fp": 0,
        "precision": 1.0,
        "recall": 1.0,
        "f1": 1.0,
        "jaccard": 1.0
      }
    },
    "04-log-y-line": {
      "error": "missing extractor dir: /Users/csweet1/Documents/projects/CRS_research/figure-recovery-suite/extractors/graph-data-extraction/results-v3/synthetic-r4-1/04-log-y-line"
    },
    "05-stacked-bar": {
      "x_tol": 1.5,
      "y_tol": 2.0,
      "scatter": {
        "summary": {
          "tp": 30,
          "fn": 0,
          "fp": 0,
          "precision": 1.0,
          "recall": 1.0,
          "f1": 1.0,
          "jaccard": 1.0
        },
        "gt_n": 30,
        "mine_n": 30,
        "by_series": {
          "cpucumtop": {
            "gt_label": "cpucumtop",
            "tp": 5,
            "fn": 0,
            "fp": 0,
            "gt_n": 5,
            "mine_n": 5
          },
          "memorycumtop": {
            "gt_label": "memorycumtop",
            "tp": 5,
            "fn": 0,
            "fp": 0,
            "gt_n": 5,
            "mine_n": 5
          },
          "iowaitcumtop": {
            "gt_label": "iowaitcumtop",
            "tp": 5,
            "fn": 0,
            "fp": 0,
            "gt_n": 5,
            "mine_n": 5
          },
          "cpuvalue": {
            "gt_label": "cpuvalue",
            "tp": 5,
            "fn": 0,
            "fp": 0,
            "gt_n": 5,
            "mine_n": 5
          },
          "memoryvalue": {
            "gt_label": "memoryvalue",
            "tp": 5,
            "fn": 0,
            "fp": 0,
            "gt_n": 5,
            "mine_n": 5
          },
          "iowaitvalue": {
            "gt_label": "iowaitvalue",
            "tp": 5,
            "fn": 0,
            "fp": 0,
            "gt_n": 5,
            "mine_n": 5
          }
        }
      },
      "curves": {
        "summary": {
          "tp": 0,
          "fn": 0,
          "fp": 0,
          "precision": 0.0,
          "recall": 0.0,
          "f1": 0.0,
          "jaccard": 0.0
        },
        "gt_n": 0,
        "mine_n": 0,
        "by_series": {}
      },
      "errbars": {
        "summary": {
          "tp": 0,
          "fn": 0,
          "fp": 0,
          "precision": 0.0,
          "recall": 0.0,
          "f1": 0.0,
          "jaccard": 0.0
        },
        "gt_n": 0,
        "mine_n": 0,
        "by_series": {}
      },
      "combined": {
        "tp": 30,
        "fn": 0,
        "fp": 0,
        "precision": 1.0,
        "recall": 1.0,
        "f1": 1.0,
        "jaccard": 1.0
      }
    },
    "06-scatter-asym-errbars": {
      "x_tol": 1.0,
      "y_tol": 1.0,
      "scatter": {
        "summary": {
          "tp": 8,
          "fn": 0,
          "fp": 0,
          "precision": 1.0,
          "recall": 1.0,
          "f1": 1.0,
          "jaccard": 1.0
        },
        "gt_n": 8,
        "mine_n": 8,
        "by_series": {
          "measurement": {
            "gt_label": "measurement",
            "tp": 8,
            "fn": 0,
            "fp": 0,
            "gt_n": 8,
            "mine_n": 8
          }
        }
      },
      "curves": {
        "summary": {
          "tp": 0,
          "fn": 0,
          "fp": 0,
          "precision": 0.0,
          "recall": 0.0,
          "f1": 0.0,
          "jaccard": 0.0
        },
        "gt_n": 0,
        "mine_n": 0,
        "by_series": {}
      },
      "errbars": {
        "summary": {
          "tp": 32,
          "fn": 0,
          "fp": 0,
          "precision": 1.0,
          "recall": 1.0,
          "f1": 1.0,
          "jaccard": 1.0
        },
        "gt_n": 32,
        "mine_n": 32,
        "by_series": {
          "errbar_caps_pooled": {
            "schema": "ErrorBarLayer",
            "tp": 32,
            "fn": 0,
            "fp": 0,
            "gt_n": 32,
            "mine_n": 32
          }
        }
      },
      "combined": {
        "tp": 40,
        "fn": 0,
        "fp": 0,
        "precision": 1.0,
        "recall": 1.0,
        "f1": 1.0,
        "jaccard": 1.0
      }
    },
    "07-dual-y-axes": {
      "x_tol": 0.3,
      "y_tol": 0.5,
      "scatter": {
        "summary": {
          "tp": 0,
          "fn": 0,
          "fp": 0,
          "precision": 0.0,
          "recall": 0.0,
          "f1": 0.0,
          "jaccard": 0.0
        },
        "gt_n": 0,
        "mine_n": 0,
        "by_series": {}
      },
      "curves": {
        "summary": {
          "tp": 48,
          "fn": 0,
          "fp": 0,
          "precision": 1.0,
          "recall": 1.0,
          "f1": 1.0,
          "jaccard": 1.0
        },
        "gt_n": 48,
        "mine_n": 48,
        "by_series": {
          "drivecurrent": {
            "gt_label": "drivecurrenta",
            "tp": 24,
            "fn": 0,
            "fp": 0,
            "gt_n": 24,
            "mine_n": 24
          },
          "cellvoltage": {
            "gt_label": "cellvoltagev",
            "tp": 24,
            "fn": 0,
            "fp": 0,
            "gt_n": 24,
            "mine_n": 24
          }
        }
      },
      "errbars": {
        "summary": {
          "tp": 0,
          "fn": 0,
          "fp": 0,
          "precision": 0.0,
          "recall": 0.0,
          "f1": 0.0,
          "jaccard": 0.0
        },
        "gt_n": 0,
        "mine_n": 0,
        "by_series": {}
      },
      "combined": {
        "tp": 48,
        "fn": 0,
        "fp": 0,
        "precision": 1.0,
        "recall": 1.0,
        "f1": 1.0,
        "jaccard": 1.0
      }
    },
    "08-percent-scinot-ticks": {
      "x_tol": 0.05,
      "y_tol": 100000.0,
      "scatter": {
        "summary": {
          "tp": 0,
          "fn": 0,
          "fp": 0,
          "precision": 0.0,
          "recall": 0.0,
          "f1": 0.0,
          "jaccard": 0.0
        },
        "gt_n": 0,
        "mine_n": 0,
        "by_series": {}
      },
      "curves": {
        "summary": {
          "tp": 14,
          "fn": 0,
          "fp": 0,
          "precision": 1.0,
          "recall": 1.0,
          "f1": 1.0,
          "jaccard": 1.0
        },
        "gt_n": 14,
        "mine_n": 14,
        "by_series": {
          "throughput": {
            "gt_label": "throughput",
            "tp": 14,
            "fn": 0,
            "fp": 0,
            "gt_n": 14,
            "mine_n": 14
          }
        }
      },
      "errbars": {
        "summary": {
          "tp": 0,
          "fn": 0,
          "fp": 0,
          "precision": 0.0,
          "recall": 0.0,
          "f1": 0.0,
          "jaccard": 0.0
        },
        "gt_n": 0,
        "mine_n": 0,
        "by_series": {}
      },
      "combined": {
        "tp": 14,
        "fn": 0,
        "fp": 0,
        "precision": 1.0,
        "recall": 1.0,
        "f1": 1.0,
        "jaccard": 1.0
      }
    },
    "09-open-markers-with-fit": {
      "x_tol": 0.3,
      "y_tol": 0.5,
      "scatter": {
        "summary": {
          "tp": 12,
          "fn": 0,
          "fp": 0,
          "precision": 1.0,
          "recall": 1.0,
          "f1": 1.0,
          "jaccard": 1.0
        },
        "gt_n": 12,
        "mine_n": 12,
        "by_series": {
          "measurement": {
            "gt_label": "measurement",
            "tp": 12,
            "fn": 0,
            "fp": 0,
            "gt_n": 12,
            "mine_n": 12
          }
        }
      },
      "curves": {
        "summary": {
          "tp": 20,
          "fn": 0,
          "fp": 0,
          "precision": 1.0,
          "recall": 1.0,
          "f1": 1.0,
          "jaccard": 1.0
        },
        "gt_n": 20,
        "mine_n": 205,
        "by_series": {
          "linearfit": {
            "gt_label": "linearfit",
            "tp": 20,
            "fn": 0,
            "fp": 0,
            "gt_n": 20,
            "mine_n": 205
          }
        }
      },
      "errbars": {
        "summary": {
          "tp": 0,
          "fn": 0,
          "fp": 0,
          "precision": 0.0,
          "recall": 0.0,
          "f1": 0.0,
          "jaccard": 0.0
        },
        "gt_n": 0,
        "mine_n": 0,
        "by_series": {}
      },
      "combined": {
        "tp": 32,
        "fn": 0,
        "fp": 0,
        "precision": 1.0,
        "recall": 1.0,
        "f1": 1.0,
        "jaccard": 1.0
      }
    },
    "10-crossing-curves": {
      "error": "missing extractor dir: /Users/csweet1/Documents/projects/CRS_research/figure-recovery-suite/extractors/graph-data-extraction/results-v3/synthetic-r4-1/10-crossing-curves"
    }
  },
  "totals": {
    "scatter": {
      "tp": 71,
      "fn": 0,
      "fp": 0,
      "precision": 1.0,
      "recall": 1.0,
      "f1": 1.0,
      "jaccard": 1.0
    },
    "curves": {
      "tp": 82,
      "fn": 0,
      "fp": 0,
      "precision": 1.0,
      "recall": 1.0,
      "f1": 1.0,
      "jaccard": 1.0
    },
    "errbars": {
      "tp": 62,
      "fn": 0,
      "fp": 0,
      "precision": 1.0,
      "recall": 1.0,
      "f1": 1.0,
      "jaccard": 1.0
    },
    "combined": {
      "tp": 215,
      "fn": 0,
      "fp": 0,
      "precision": 1.0,
      "recall": 1.0,
      "f1": 1.0,
      "jaccard": 1.0
    }
  }
}